pypckdummy/__init__.py
pypckdummy/practice_reaction.py
pypckdummy/todays_practice.py
tests/__init__.py
pypck_dummy-0.0.12.dist-info/METADATA
pypck_dummy-0.0.12.dist-info/WHEEL
pypck_dummy-0.0.12.dist-info/top_level.txt
pypck_dummy-0.0.12.dist-info/RECORD
