Metadata-Version: 2.1
Name: pypck-dummy
Version: 0.0.12
Summary: This is a test.
Home-page: https://gitub.com/...
Author: 
Author-email: 
